huoshui_pdf_translator/__init__.py
huoshui_pdf_translator/main.py
huoshui_pdf_translator-0.1.1.dist-info/METADATA
huoshui_pdf_translator-0.1.1.dist-info/WHEEL
huoshui_pdf_translator-0.1.1.dist-info/entry_points.txt
huoshui_pdf_translator-0.1.1.dist-info/licenses/LICENSE
huoshui_pdf_translator-0.1.1.dist-info/RECORD
