Metadata-Version: 2.4
Name: huoshui-pdf-translator
Version: 0.1.1
Summary: AI-powered PDF translation assistant using PDFMathTranslate-next, specialized for academic papers with mathematical formulas
Project-URL: Homepage, https://github.com/huoshuiai/huoshui-pdf-translator
Project-URL: Bug Reports, https://github.com/huoshuiai/huoshui-pdf-translator/issues
Project-URL: Source, https://github.com/huoshuiai/huoshui-pdf-translator
Project-URL: Documentation, https://github.com/huoshuiai/huoshui-pdf-translator#readme
Author-email: Huoshui AI <contact@huoshui.ai>
License: Apache-2.0
License-File: LICENSE
Keywords: academic,fastmcp,mathematics,mcp,pdf,translation
Classifier: Development Status :: 4 - Beta
Classifier: Intended Audience :: Developers
Classifier: Intended Audience :: Science/Research
Classifier: License :: OSI Approved :: Apache Software License
Classifier: Programming Language :: Python :: 3
Classifier: Programming Language :: Python :: 3.12
Classifier: Topic :: Scientific/Engineering
Classifier: Topic :: Text Processing :: Linguistic
Requires-Python: >=3.12
Requires-Dist: fastmcp>=2.10.1
Requires-Dist: pdf2zh-next>=2.3.3
Requires-Dist: pydantic>=2.5.0
Provides-Extra: dev
Requires-Dist: black>=23.0.0; extra == 'dev'
Requires-Dist: pytest-asyncio>=0.21.0; extra == 'dev'
Requires-Dist: pytest>=7.4.0; extra == 'dev'
Requires-Dist: ruff>=0.1.0; extra == 'dev'
